irish_pipeline/__init__.py
irish_pipeline/__main__.py
irish_pipeline/cli.py
irish_pipeline/config.py
irish_pipeline/database.py
irish_pipeline/schema.py
irish_pipeline-0.1.0.dist-info/licenses/LICENSE
irish_pipeline-0.1.0.dist-info/METADATA
irish_pipeline-0.1.0.dist-info/WHEEL
irish_pipeline-0.1.0.dist-info/entry_points.txt
irish_pipeline-0.1.0.dist-info/top_level.txt
irish_pipeline-0.1.0.dist-info/RECORD
