Metadata-Version: 2.4
Name: irish-pipeline
Version: 0.1.0
Summary: Tools to inspect schemas and load Irish data into Postgres database
Author-email: Shyam Kumar Ray Yadav <shyamkumar.rayyadav@gwdg.de>
Project-URL: Homepage, https://gitlab.gwdg.de/srayyad/irish_data_crc_development
Classifier: Programming Language :: Python :: 3.11
Classifier: Operating System :: OS Independent
Requires-Python: >=3.11
License-File: LICENSE
Requires-Dist: pandas>=2.2.0
Requires-Dist: PyYAML>=6.0.1
Requires-Dist: SQLAlchemy>=2.0.25
Requires-Dist: python-dotenv>=0.21.0
Requires-Dist: click
Dynamic: license-file
